carvemegut/__init__.py
carvemegut/config.cfg
carvemegut/cli/__init__.py
carvemegut/cli/benchmark.py
carvemegut/cli/benchmark_cdiff.py
carvemegut/cli/benchmark_new.py
carvemegut/cli/build_universe.py
carvemegut/cli/carve.py
carvemegut/cli/carve_old.py
carvemegut/cli/curate_universe.py
carvemegut/cli/gapfill.py
carvemegut/cli/merge_community.py
carvemegut/cli/original_carve.py
carvemegut/reconstruction/__init__.py
carvemegut/reconstruction/benchmark.py
carvemegut/reconstruction/carving.py
carvemegut/reconstruction/diamond.py
carvemegut/reconstruction/eggnog.py
carvemegut/reconstruction/gapfilling.py
carvemegut/reconstruction/ncbi_download.py
carvemegut/reconstruction/scoring.py
carvemegut/reconstruction/utils.py
carvemegut/universe/__init__.py
carvemegut/universe/annotate.py
carvemegut/universe/curation.py
carvemegut/universe/download.py
carvemegut-0.3.8.dist-info/METADATA
carvemegut-0.3.8.dist-info/WHEEL
carvemegut-0.3.8.dist-info/entry_points.txt
carvemegut-0.3.8.dist-info/top_level.txt
carvemegut-0.3.8.dist-info/RECORD
