Metadata-Version: 2.1
Name: carvemegut
Version: 0.3.8
Summary: A Python package for metabolic modeling
Home-page: https://github.com/yourusername/carvemegut
Author: Arianna Basile
Author-email: basilearianna1@gmail.com
License: MIT
Classifier: Programming Language :: Python :: 3
Classifier: License :: OSI Approved :: MIT License
Classifier: Operating System :: OS Independent
Requires-Python: >=3.7
Requires-Dist: requests
